LICENSE
MANIFEST.in
README
setup.py
django_emails.egg-info/PKG-INFO
django_emails.egg-info/SOURCES.txt
django_emails.egg-info/dependency_links.txt
django_emails.egg-info/not-zip-safe
django_emails.egg-info/top_level.txt
emails/__init__.py
emails/admin.py
emails/engine.py
emails/models.py
emails/settings.py
emails/signals.py
emails/tests.py
emails/management/__init__.py
emails/management/commands/__init__.py
emails/management/commands/sendbatch.py
emails/templates/emails/notification.html
emails/templates/emails/test.html
example/__init__.py
example/local_settings.py
example/manage.py
example/settings.py
example/urls.py
example/emails/__init__.py
example/emails/admin.py
example/emails/engine.py
example/emails/models.py
example/emails/settings.py
example/emails/signals.py
example/emails/tests.py
example/emails/management/__init__.py
example/emails/management/commands/__init__.py
example/emails/management/commands/sendbatch.py
example/example/__init__.py
example/example/admin.py
example/example/models.py
example/example/tests.py
example/example/views.py