Metadata-Version: 1.1
Name: django-emails
Version: 1.0
Summary: Cron email sender.
Home-page: https://github.com/matllubos/django-emails
Author: Lubos Matl
Author-email: matllubos@gmail.com
License: GPL
Keywords: django,admin,emails
Platform: UNKNOWN
Classifier: Environment :: Web Environment
Classifier: Framework :: Django
Classifier: Intended Audience :: Developers
Classifier: Intended Audience :: End Users/Desktop
Classifier: License :: OSI Approved :: GNU General Public License (GPL)
Classifier: Natural Language :: Czech
Classifier: Operating System :: OS Independent
Classifier: Programming Language :: Python
Classifier: Topic :: Internet :: WWW/HTTP :: Dynamic Content
Classifier: Topic :: Internet :: WWW/HTTP :: Site Management
